{
    "menu": [
        {
            "blankspace" : false,
            "menuId" : "menu-add",
            "is" : "menu-link",
            "hyperlink" : "#",
            "menuLinkName" : "Add",
            "dropdown" : true
        },

        {
            "blankspace" : false,
            "menuId" : "menu-send",
            "is" : "menu-link",
            "hyperlink" : "#",
            "menuLinkName" : "Send",
            "dropdown" : false
        },

        {
            
            "blankspace" : false,
            "menuId" : "menu-delete",
            "is" : "menu-link",
            "hyperlink" : "#",
            "menuLinkName" : "Delete",
            "dropdown" : true
        },

        {
            "blankspace" : false,
            "menuId" : "menu-monitoring",
            "is" : "menu-link",
            "hyperlink" : "#",
            "menuLinkName" : "Monitoring",
            "dropdown" : false
        },

        {
            "blankspace" : true
        },

        {
            "blankspace" : true
        },

        {
            "blankspace" : true
        },

        {
            "blankspace" : false,
            "menuId" : "header-space",
            "is" : "header-space"
        }
    ]
}